[
    {
        "id": 1,
        "address": "123 Maple Street",
        "city": "San Francisco",
        "state": "CA",
        "zip_code": "94107",
        "price": 1200000,
        "bedrooms": 3,
        "bathrooms": 2,
        "square_feet": 1500,
        "lot_size": 5000,
        "year_built": 1995,
        "description": "Beautiful single-family home with a large backyard.",
        "image_url":
            ["https://ssl.cdn-redfin.com/photo/9/bigphoto/729/424031729_0.jpg", 
            "https://ssl.cdn-redfin.com/photo/9/bigphoto/729/424031729_1_0.jpg",
            "https://ssl.cdn-redfin.com/photo/9/bigphoto/729/424031729_2_0.jpg",
            "https://ssl.cdn-redfin.com/photo/9/bigphoto/729/424031729_4_0.jpg",
            "https://ssl.cdn-redfin.com/photo/9/bigphoto/729/424031729_5_0.jpg",
            "https://ssl.cdn-redfin.com/photo/9/bigphoto/729/424031729_6_0.jpg"
        ]
    },
    {
        "id": 2,
        "address": "456 Oak Avenue",
        "city": "Los Angeles",
        "state": "CA",
        "zip_code": "90001",
        "price": 850000,
        "bedrooms": 2,
        "bathrooms": 1,
        "square_feet": 1200,
        "lot_size": 3000,
        "year_built": 1980,
        "description": "Charming bungalow in a quiet neighborhood.",
        "image_url": [
            "https://ssl.cdn-redfin.com/photo/27/bigphoto/407/424047407_4.jpg",
            "https://ssl.cdn-redfin.com/photo/27/bigphoto/407/424047407_1_4.jpg",
            "https://ssl.cdn-redfin.com/photo/27/bigphoto/407/424047407_2_4.jpg",
            "https://ssl.cdn-redfin.com/photo/27/bigphoto/407/424047407_4_4.jpg",
            "https://ssl.cdn-redfin.com/photo/27/bigphoto/407/424047407_7_4.jpg"
        ]
    },
    {
        "id": 3,
        "address": "789 Pine Lane",
        "city": "San Diego",
        "state": "CA",
        "zip_code": "92103",
        "price": 950000,
        "bedrooms": 4,
        "bathrooms": 3,
        "square_feet": 2000,
        "lot_size": 4000,
        "year_built": 2005,
        "description": "Spacious family home with modern amenities.",
        "image_url": [
            "https://ssl.cdn-redfin.com/photo/8/bigphoto/916/ML81965916_0.jpg",
            "https://ssl.cdn-redfin.com/photo/8/mbphoto/916/genMid.ML81965916_21_0.jpg",
            "https://ssl.cdn-redfin.com/photo/8/bigphoto/916/ML81965916_2_0.jpg"
        ]
    },
    {
        "id": 4,
        "address": "101 Birch Road",
        "city": "Sacramento",
        "state": "CA",
        "zip_code": "95814",
        "price": 500000,
        "bedrooms": 3,
        "bathrooms": 2,
        "square_feet": 1400,
        "lot_size": 3500,
        "year_built": 1975,
        "description": "Cozy home with a large deck and garden.",
        "image_url": [
            "https://ssl.cdn-redfin.com/photo/8/bigphoto/235/ML81970235_0.jpg",
            "https://ssl.cdn-redfin.com/photo/8/mbphoto/235/genMid.ML81970235_17_0.jpg",
            "https://ssl.cdn-redfin.com/photo/8/mbphoto/235/genMid.ML81970235_51_0.jpg"
        ]
    },
    {
        "id": 5,
        "address": "202 Cedar Drive",
        "city": "San Jose",
        "state": "CA",
        "zip_code": "95112",
        "price": 1100000,
        "bedrooms": 5,
        "bathrooms": 4,
        "square_feet": 2500,
        "lot_size": 6000,
        "year_built": 2010,
        "description": "Luxurious home with a pool and outdoor kitchen.",
        "image_url": [
            "https://ssl.cdn-redfin.com/photo/8/bigphoto/755/ML81969755_0.jpg",
            "https://ssl.cdn-redfin.com/photo/8/mbphoto/755/genMid.ML81969755_2_0.jpg",
            "https://ssl.cdn-redfin.com/photo/8/mbphoto/755/genMid.ML81969755_7_0.jpg"
        ]
    },

    {
        "id": 6,
        "address": "303 Elm Street",
        "city": "Fresno",
        "state": "CA",
        "zip_code": "93711",
        "price": 400000,
        "bedrooms": 3,
        "bathrooms": 2,
        "square_feet": 1300,
        "lot_size": 3200,
        "year_built": 1990,
        "description": "Affordable family home with a nice garden.",
        "image_url": [
            "https://ssl.cdn-redfin.com/photo/9/bigphoto/464/424035464_1.jpg",
            "https://ssl.cdn-redfin.com/photo/9/mbphoto/464/genMid.424035464_8_1.jpg",
            "https://ssl.cdn-redfin.com/photo/9/mbphoto/464/genMid.424035464_24_2.jpg"
        ]
    },
    {
        "id": 7,
        "address": "404 Walnut Lane",
        "city": "Bakersfield",
        "state": "CA",
        "zip_code": "93309",
        "price": 450000,
        "bedrooms": 4,
        "bathrooms": 3,
        "square_feet": 1600,
        "lot_size": 3800,
        "year_built": 1985,
        "description": "Comfortable home with a newly renovated kitchen.",
        "image_url": [
            "https://ssl.cdn-redfin.com/photo/9/bigphoto/022/424040022_0.jpg",
            "https://ssl.cdn-redfin.com/photo/9/mbphoto/022/genMid.424040022_14_0.jpg",
            "https://ssl.cdn-redfin.com/photo/9/mbphoto/022/genMid.424040022_44_0.jpg"
        ]
    },
    {
        "id": 8,
        "address": "505 Cypress Court",
        "city": "Oakland",
        "state": "CA",
        "zip_code": "94601",
        "price": 750000,
        "bedrooms": 3,
        "bathrooms": 2,
        "square_feet": 1400,
        "lot_size": 2500,
        "year_built": 1998,
        "description": "Modern home with easy access to downtown.",
        "image_url": [
            "https://ssl.cdn-redfin.com/photo/9/bigphoto/719/424036719_0.jpg",
            "https://ssl.cdn-redfin.com/photo/9/mbphoto/719/genMid.424036719_11_0.jpg",
            "https://ssl.cdn-redfin.com/photo/9/mbphoto/719/genMid.424036719_34_0.jpg"
        ]
    },
    {
        "id": 9,
        "address": "606 Redwood Terrace",
        "city": "Berkeley",
        "state": "CA",
        "zip_code": "94704",
        "price": 900000,
        "bedrooms": 3,
        "bathrooms": 2,
        "square_feet": 1800,
        "lot_size": 2700,
        "year_built": 2001,
        "description": "Stylish home with a great view of the bay.",
        "image_url": [
            "https://ssl.cdn-redfin.com/photo/8/bigphoto/913/ML81968913_2.jpg",
            "https://ssl.cdn-redfin.com/photo/8/mbphoto/913/genMid.ML81968913_20_2.jpg",
            "https://ssl.cdn-redfin.com/photo/8/mbphoto/913/genMid.ML81968913_60_1.jpg"
        ]
    },
    {
        "id": 10,
        "address": "707 Willow Way",
        "city": "Palo Alto",
        "state": "CA",
        "zip_code": "94301",
        "price": 2000000,
        "bedrooms": 4,
        "bathrooms": 3,
        "square_feet": 2200,
        "lot_size": 4500,
        "year_built": 2015,
        "description": "Elegant home in a prestigious neighborhood.",
        "image_url": [
            "https://ssl.cdn-redfin.com/photo/77/bigphoto/569/424039569_2.jpg",
            "https://ssl.cdn-redfin.com/photo/77/mbphoto/569/genMid.424039569_10_2.jpg",
            "https://ssl.cdn-redfin.com/photo/77/mbphoto/569/genMid.424039569_30_2.jpg"
        ]
    },
    {
        "id": 11,
        "address": "808 Chestnut Blvd",
        "city": "Santa Clara",
        "state": "CA",
        "zip_code": "95050",
        "price": 950000,
        "bedrooms": 3,
        "bathrooms": 2,
        "square_feet": 1900,
        "lot_size": 3700,
        "year_built": 2000,
        "description": "Conveniently located home with a spacious layout.",
        "image_url": "https://example.com/images/house11.jpg"
    },
    {
        "id": 12,
        "address": "909 Spruce Street",
        "city": "Sunnyvale",
        "state": "CA",
        "zip_code": "94086",
        "price": 1300000,
        "bedrooms": 5,
        "bathrooms": 3,
        "square_feet": 2600,
        "lot_size": 4900,
        "year_built": 2018,
        "description": "Newly built home with high-end finishes.",
        "image_url": "https://example.com/images/house12.jpg"
    },
    {
        "id": 13,
        "address": "1001 Poplar Place",
        "city": "Mountain View",
        "state": "CA",
        "zip_code": "94040",
        "price": 1800000,
        "bedrooms": 4,
        "bathrooms": 4,
        "square_feet": 2400,
        "lot_size": 4600,
        "year_built": 2012,
        "description": "Spacious and modern home in a tech hub.",
        "image_url": "https://example.com/images/house13.jpg"
    },
    {
        "id": 14,
        "address": "1102 Palm Drive",
        "city": "Irvine",
        "state": "CA",
        "zip_code": "92602",
        "price": 1400000,
        "bedrooms": 4,
        "bathrooms": 3,
        "square_feet": 2100,
        "lot_size": 4100,
        "year_built": 2016,
        "description": "Contemporary home in a family-friendly community.",
        "image_url": "https://example.com/images/house14.jpg"
    },
    {
        "id": 15,
        "address": "1203 Magnolia Avenue",
        "city": "Riverside",
        "state": "CA",
        "zip_code": "92501",
        "price": 600000,
        "bedrooms": 3,
        "bathrooms": 2,
        "square_feet": 1700,
        "lot_size": 3500,
        "year_built": 1987,
        "description": "Well-maintained home with a lovely garden.",
        "image_url": "https://example.com/images/house15.jpg"
    },
    {
        "id": 16,
        "address": "1304 Maplewood Drive",
        "city": "Chula Vista",
        "state": "CA",
        "zip_code": "91910",
        "price": 800000,
        "bedrooms": 4,
        "bathrooms": 2,
        "square_feet": 2000,
        "lot_size": 3000,
        "year_built": 2003,
        "description": "Comfortable home with a spacious living area.",
        "image_url": "https://example.com/images/house16.jpg"
    },
    {
        "id": 17,
        "address": "1405 Sycamore Lane",
        "city": "Anaheim",
        "state": "CA",
        "zip_code": "92801",
        "price": 700000,
        "bedrooms": 3,
        "bathrooms": 2,
        "square_feet": 1500,
        "lot_size": 2900,
        "year_built": 1993,
        "description": "Lovely home close to parks and schools.",
        "image_url": "https://example.com/images/house17.jpg"
    },
    {
        "id": 18,
        "address": "1506 Laurel Road",
        "city": "Long Beach",
        "state": "CA",
        "zip_code": "90802",
        "price": 850000,
        "bedrooms": 4,
        "bathrooms": 3,
        "square_feet": 1800,
        "lot_size": 3100,
        "year_built": 1999,
        "description": "Charming home with a great layout and location.",
        "image_url": "https://example.com/images/house18.jpg"
    },
    {
        "id": 19,
        "address": "1607 Maple Court",
        "city": "Santa Monica",
        "state": "CA",
        "zip_code": "90405",
        "price": 2500000,
        "bedrooms": 5,
        "bathrooms": 4,
        "square_feet": 3000,
        "lot_size": 5000,
        "year_built": 2019,
        "description": "Luxurious home with a view of the ocean.",
        "image_url": "https://example.com/images/house19.jpg"
    },
    {
        "id": 20,
        "address": "1708 Pine Ridge",
        "city": "Pasadena",
        "state": "CA",
        "zip_code": "91101",
        "price": 1600000,
        "bedrooms": 4,
        "bathrooms": 3,
        "square_feet": 2200,
        "lot_size": 4100,
        "year_built": 2017,
        "description": "Modern home with a beautiful design.",
        "image_url": "https://example.com/images/house20.jpg"
    },
    {
        "id": 21,
        "address": "123 Maple Street",
        "city": "San Francisco",
        "state": "CA",
        "zip_code": "94107",
        "price": 1200000,
        "bedrooms": 3,
        "bathrooms": 2,
        "square_feet": 1500,
        "lot_size": 5000,
        "year_built": 1995,
        "description": "Beautiful single-family home with a large backyard.",
        "image_url": "https://example.com/images/house1.jpg"
    }, 
    {
        "id": 22,
        "address": "456 Oak Avenue",
        "city": "Los Angeles",
        "state": "CA",
        "zip_code": "90001",
        "price": 850000,
        "bedrooms": 2,
        "bathrooms": 1,
        "square_feet": 1200,
        "lot_size": 3000,
        "year_built": 1980,
        "description": "Charming bungalow in a quiet neighborhood.",
        "image_url": "https://example.com/images/house2.jpg"
    },

    {
        "id": 23,
        "address": "789 Pine Lane",
        "city": "San Diego",
        "state": "CA",
        "zip_code": "92103",
        "price": 950000,
        "bedrooms": 4,
        "bathrooms": 3,
        "square_feet": 2000,
        "lot_size": 4000,
        "year_built": 2005,
        "description": "Spacious family home with modern amenities.",
        "image_url": "https://example.com/images/house3.jpg"
    },
    {
        "id": 24,
        "address": "101 Birch Road",
        "city": "Sacramento",
        "state": "CA",
        "zip_code": "95814",
        "price": 500000,
        "bedrooms": 3,
        "bathrooms": 2,
        "square_feet": 1400,
        "lot_size": 3500,
        "year_built": 1975,
        "description": "Cozy home with a large deck and garden.",
        "image_url": "https://example.com/images/house4.jpg"
    },
    {
        "id": 25,
        "address": "202 Cedar Drive",
        "city": "San Jose",
        "state": "CA",
        "zip_code": "95112",
        "price": 1100000,
        "bedrooms": 5,
        "bathrooms": 4,
        "square_feet": 2500,
        "lot_size": 6000,
        "year_built": 2010,
        "description": "Luxurious home with a pool and outdoor kitchen.",
        "image_url": "https://example.com/images/house5.jpg"
    }
    
]
